pydiamond/__init__.py
pydiamond/__init__.pyi
pydiamond/py.typed
pydiamond/version.py
pydiamond/_patch/__init__.py
pydiamond/_patch/_base.py
pydiamond/_patch/_collector.py
pydiamond/_patch/controller.py
pydiamond/_patch/py.typed
pydiamond/_patch/plugins/__init__.py
pydiamond/_patch/plugins/environment.py
pydiamond/_patch/plugins/fix_typing.py
pydiamond/_patch/plugins/py.typed
pydiamond/_patch/plugins/pygame_patch.py
pydiamond/_patch/utils/__init__.py
pydiamond/_patch/utils/py.typed
pydiamond/_patch/utils/pygame.py
pydiamond/audio/__init__.py
pydiamond/audio/mixer.py
pydiamond/audio/music.py
pydiamond/audio/py.typed
pydiamond/audio/sound.py
pydiamond/environ/__init__.py
pydiamond/environ/executable.py
pydiamond/environ/py.typed
pydiamond/graphics/__init__.py
pydiamond/graphics/_draw.py
pydiamond/graphics/_gradients.py
pydiamond/graphics/_gradients.pyi
pydiamond/graphics/_transform.py
pydiamond/graphics/animation.py
pydiamond/graphics/color.py
pydiamond/graphics/drawable.py
pydiamond/graphics/font.py
pydiamond/graphics/gradients.py
pydiamond/graphics/grid.py
pydiamond/graphics/image.py
pydiamond/graphics/movable.py
pydiamond/graphics/progress.py
pydiamond/graphics/py.typed
pydiamond/graphics/renderer.py
pydiamond/graphics/shape.py
pydiamond/graphics/sprite.py
pydiamond/graphics/surface.py
pydiamond/graphics/text.py
pydiamond/graphics/transformable.py
pydiamond/gui/__init__.py
pydiamond/gui/focus.py
pydiamond/gui/py.typed
pydiamond/gui/scene.py
pydiamond/gui/tools/__init__.py
pydiamond/gui/tools/_grid.py
pydiamond/gui/tools/py.typed
pydiamond/gui/tools/view.py
pydiamond/gui/widgets/__init__.py
pydiamond/gui/widgets/_renderer.py
pydiamond/gui/widgets/abc.py
pydiamond/gui/widgets/button.py
pydiamond/gui/widgets/checkbox.py
pydiamond/gui/widgets/entry.py
pydiamond/gui/widgets/form.py
pydiamond/gui/widgets/grid.py
pydiamond/gui/widgets/image.py
pydiamond/gui/widgets/label.py
pydiamond/gui/widgets/py.typed
pydiamond/gui/widgets/scale.py
pydiamond/gui/widgets/scroll.py
pydiamond_engine-1.0.0.dev3.dist-info/LICENSE
pydiamond_engine-1.0.0.dev3.dist-info/WHEEL
pydiamond_engine-1.0.0.dev3.dist-info/METADATA
pydiamond_engine-1.0.0.dev3.dist-info/RECORD
