Metadata-Version: 2.1
Name: pydiamond-engine
Version: 1.0.0.dev3
Summary: pygame-based game engine
Keywords: game,game-engine,game-development,pygame,pygame-library,game-engine-2d
Author-email: FrankySnow9 <clairicia.rcj.francis@gmail.com>
Requires-Python: >=3.10
Classifier: Development Status :: 2 - Pre-Alpha
Classifier: Intended Audience :: Developers
Classifier: License :: OSI Approved :: GNU General Public License v3 (GPLv3)
Classifier: Operating System :: OS Independent
Classifier: Programming Language :: Python
Classifier: Programming Language :: Python :: 3
Classifier: Programming Language :: Python :: 3 :: Only
Classifier: Programming Language :: Python :: 3.10
Classifier: Topic :: Software Development :: Libraries :: pygame
Classifier: Typing :: Typed
Requires-Dist: pygame==2.1.2
Requires-Dist: cryptography~=38.0.1
Requires-Dist: typing_extensions>=4.4.0,<5
Project-URL: Homepage, https://github.com/francis-clairicia/PyDiamond
